pytunneler/__init__.py
pytunneler/client/__init__.py
pytunneler/client/client.py
pytunneler/server/__init__.py
pytunneler/server/server.py
pytunneler/utils/__init__.py
pytunneler/utils/commands.py
pytunneler/utils/host_hex.py
pytunneler/utils/network.py
pytunneler/utils/packet.py
pytunneler-0.1.1.dist-info/LICENSE
pytunneler-0.1.1.dist-info/METADATA
pytunneler-0.1.1.dist-info/WHEEL
pytunneler-0.1.1.dist-info/RECORD
